<?xml version="1.0" encoding="UTF-8" standalone="yes" ?>
<program>
  <header>
    <applicationBuildName></applicationBuildName>
    <applicationBuildNumber>0</applicationBuildNumber>
    <applicationBuildType>release</applicationBuildType>
    <applicationName>Покет Код</applicationName>
    <applicationVersion>1.2.4</applicationVersion>
    <catrobatLanguageVersion>1.17</catrobatLanguageVersion>
    <customResolution>false</customResolution>
    <dateTimeUpload></dateTimeUpload>
    <description></description>
    <deviceName>HRY-LX1T</deviceName>
    <gitRemoteUrl></gitRemoteUrl>
    <isCastProject>false</isCastProject>
    <landscapeMode>true</landscapeMode>
    <listeningLanguageTag></listeningLanguageTag>
    <mediaLicense></mediaLicense>
    <notesAndCredits></notesAndCredits>
    <physicsHeightArea>2.0</physicsHeightArea>
    <physicsWidthArea>3.0</physicsWidthArea>
    <platform>Android</platform>
    <platformVersion>29</platformVersion>
    <programLicense></programLicense>
    <programName>Чикен ган</programName>
    <remixOf></remixOf>
    <scenesEnabled>true</scenesEnabled>
    <screenHeight>1080</screenHeight>
    <screenMode>STRETCH</screenMode>
    <screenWidth>2139</screenWidth>
    <tags></tags>
    <url></url>
    <userHandle></userHandle>
  </header>
  <settings/>
  <scenes>
    <scene sceneId="5ebd7d20-98aa-4db7-89f3-5e28a62e60f5">
      <name>Меню</name>
      <objectList>
        <object type="Sprite" spriteId="958627e0-c7fd-4377-836e-539f490cd08a" name="Фон">
          <lookList>
            <look fileName="Фон.png" lookId="f736d949-a5a2-499c-8ffb-43701676b35e" name="Фон">
              <isWebRequest>false</isWebRequest>
              <valid>true</valid>
            </look>
          </lookList>
          <soundList/>
          <scriptList/>
          <nfcTagList/>
          <userVariables/>
          <userLists/>
          <userDefinedBrickList/>
        </object>
        <object type="Sprite" spriteId="8a4939ee-56af-45f9-b89e-a597b1fb5bb7" name="Мой актер или объект">
          <lookList>
            <look fileName="Мой актер или объект_#0.png" lookId="7ca3b833-0381-4049-a4b9-5a5ed9d9fbb6" name="Мой актер или объект (1)">
              <isWebRequest>false</isWebRequest>
              <valid>true</valid>
            </look>
            <look fileName="Мой актер или объект_#1.png" lookId="276c1d94-9918-46dc-b810-24da2359032c" name="Мой актер или объект (2)">
              <isWebRequest>false</isWebRequest>
              <valid>true</valid>
            </look>
            <look fileName="Мой актер или объект_#2.png" lookId="64c3cfd3-d63d-46d9-9dd1-e6aa6d8bec9b" name="Мой актер или объект (3)">
              <isWebRequest>false</isWebRequest>
              <valid>true</valid>
            </look>
            <look fileName="Мой актер или объект_#3.png" lookId="3fb60607-9af5-4aee-91d6-57cc5a98c96c" name="Мой актер или объект (4)">
              <isWebRequest>false</isWebRequest>
              <valid>true</valid>
            </look>
          </lookList>
          <soundList/>
          <scriptList>
            <script type="StartScript" posX="0.0" posY="0.0">
              <brickList>
                <brick type="PlaceAtBrick">
                  <brickId>75dc9e74-91d3-4b85-b2b9-a2d30fdec9b3</brickId>
                  <commentedOut>false</commentedOut>
                  <formulaList>
                    <formula category="X_POSITION">
                      <additionalChildren/>
                      <type>NUMBER</type>
                      <value>38</value>
                    </formula>
                    <formula category="Y_POSITION">
                      <additionalChildren/>
                      <rightChild>
                        <additionalChildren/>
                        <type>NUMBER</type>
                        <value>44</value>
                      </rightChild>
                      <type>OPERATOR</type>
                      <value>MINUS</value>
                    </formula>
                  </formulaList>
                </brick>
              </brickList>
              <commentedOut>false</commentedOut>
              <scriptId>f5556317-919b-4166-bb36-0448fc58ab24</scriptId>
            </script>
            <script type="StartScript" posX="0.0" posY="0.0">
              <brickList>
                <brick type="ForeverBrick">
                  <brickId>0fecad04-ac9f-4cee-990e-4f4ac145d21c</brickId>
                  <commentedOut>false</commentedOut>
                  <loopBricks>
                    <brick type="WaitBrick">
                      <brickId>e5eaad14-c7b9-407d-abb8-d6c56dca88f8</brickId>
                      <commentedOut>false</commentedOut>
                      <formulaList>
                        <formula category="TIME_TO_WAIT_IN_SECONDS">
                          <additionalChildren/>
                          <type>NUMBER</type>
                          <value>0.3</value>
                        </formula>
                      </formulaList>
                    </brick>
                    <brick type="NextLookBrick">
                      <brickId>f2328d6b-8df1-44d2-a102-fae22b39bca6</brickId>
                      <commentedOut>false</commentedOut>
                    </brick>
                  </loopBricks>
                </brick>
              </brickList>
              <commentedOut>false</commentedOut>
              <scriptId>beabe661-2b37-4fcc-a937-137b17ced143</scriptId>
            </script>
          </scriptList>
          <nfcTagList/>
          <userVariables/>
          <userLists/>
          <userDefinedBrickList/>
        </object>
        <object type="Sprite" spriteId="8f73ec2e-9e66-4109-a96a-dbfc10907ed5" name="Мой актер или объект (1)">
          <lookList>
            <look fileName="Мой актер или объект.png" lookId="2564f54c-3de4-458e-bd66-c9ef635503cd" name="Мой актер или объект (1)">
              <isWebRequest>false</isWebRequest>
              <valid>true</valid>
            </look>
          </lookList>
          <soundList/>
          <scriptList>
            <script type="StartScript" posX="0.0" posY="0.0">
              <brickList>
                <brick type="PlaceAtBrick">
                  <brickId>ea76fc9c-2772-49e4-ba15-e433f673bf84</brickId>
                  <commentedOut>false</commentedOut>
                  <formulaList>
                    <formula category="X_POSITION">
                      <additionalChildren/>
                      <rightChild>
                        <additionalChildren/>
                        <type>NUMBER</type>
                        <value>472</value>
                      </rightChild>
                      <type>OPERATOR</type>
                      <value>MINUS</value>
                    </formula>
                    <formula category="Y_POSITION">
                      <additionalChildren/>
                      <type>NUMBER</type>
                      <value>66</value>
                    </formula>
                  </formulaList>
                </brick>
              </brickList>
              <commentedOut>false</commentedOut>
              <scriptId>ea254861-fcab-418e-a231-35c59fe91429</scriptId>
            </script>
            <script type="WhenScript" posX="0.0" posY="0.0">
              <brickList>
                <brick type="SceneStartBrick">
                  <brickId>2097c1a5-1cca-4e80-ad54-c10815927860</brickId>
                  <commentedOut>false</commentedOut>
                  <sceneToStart>Сандбох</sceneToStart>
                </brick>
              </brickList>
              <commentedOut>false</commentedOut>
              <scriptId>fccbafa0-e144-4be8-a5e9-dc00e0e18ed5</scriptId>
            </script>
          </scriptList>
          <nfcTagList/>
          <userVariables/>
          <userLists/>
          <userDefinedBrickList/>
        </object>
      </objectList>
    </scene>
    <scene sceneId="30c12a58-11eb-422c-a83c-875cf24bca53">
      <name>Сандбох</name>
      <objectList>
        <object type="Sprite" spriteId="d68be8e5-18b6-4046-9e85-995c3df48618" name="Фон">
          <lookList>
            <look fileName="Фон.png" lookId="21ffffdd-9aba-41fd-8b8d-d42faae9d737" name="Фон">
              <isWebRequest>false</isWebRequest>
              <valid>true</valid>
            </look>
          </lookList>
          <soundList/>
          <scriptList/>
          <nfcTagList/>
          <userVariables/>
          <userLists/>
          <userDefinedBrickList/>
        </object>
        <object type="Sprite" spriteId="cf1c35ed-12a3-4729-89df-ffa58857c5db" name="Игрок">
          <lookList>
            <look fileName="Мой актер или объект_#2.png" lookId="d4d81a22-9d70-48d2-aba3-e4e3f52c6b91" name="Игрок">
              <isWebRequest>false</isWebRequest>
              <valid>true</valid>
            </look>
          </lookList>
          <soundList/>
          <scriptList>
            <script type="StartScript" posX="0.0" posY="0.0">
              <brickList>
                <brick type="SetPhysicsObjectTypeBrick">
                  <brickId>ed597fb9-7254-4c78-86ce-eb9d9efdbb48</brickId>
                  <commentedOut>false</commentedOut>
                  <type>FIXED</type>
                </brick>
                <brick type="ForeverBrick">
                  <brickId>a4ed4bb7-647f-4a1c-bf5b-1e0cb6240eaf</brickId>
                  <commentedOut>false</commentedOut>
                  <loopBricks>
                    <brick type="IfThenLogicBeginBrick">
                      <brickId>e8ddd927-6f6a-4a77-a312-d38e57cef8f4</brickId>
                      <commentedOut>false</commentedOut>
                      <formulaList>
                        <formula category="IF_CONDITION">
                          <additionalChildren/>
                          <type>SENSOR</type>
                          <value>FINGER_TOUCHED</value>
                        </formula>
                      </formulaList>
                      <ifBranchBricks>
                        <brick type="PointInDirectionBrick">
                          <brickId>48b1a1e7-3f73-4638-af3d-6b629ea30e6d</brickId>
                          <commentedOut>false</commentedOut>
                          <formulaList>
                            <formula category="DEGREES">
                              <additionalChildren/>
                              <type>USER_VARIABLE</type>
                              <value>Указ</value>
                            </formula>
                          </formulaList>
                        </brick>
                        <brick type="MoveNStepsBrick">
                          <brickId>bac2bab5-e6a8-4ef5-96a8-4f6f133b3fb7</brickId>
                          <commentedOut>false</commentedOut>
                          <formulaList>
                            <formula category="STEPS">
                              <additionalChildren/>
                              <type>NUMBER</type>
                              <value>12</value>
                            </formula>
                          </formulaList>
                        </brick>
                      </ifBranchBricks>
                    </brick>
                  </loopBricks>
                </brick>
              </brickList>
              <commentedOut>false</commentedOut>
              <scriptId>1a2cb628-2538-4692-a54d-91b8a6fdbdfa</scriptId>
            </script>
          </scriptList>
          <nfcTagList/>
          <userVariables/>
          <userLists/>
          <userDefinedBrickList/>
        </object>
        <object type="Sprite" spriteId="ced42401-5fd3-4e17-90bd-a1d21e8de3df" name="Джойстик">
          <lookList>
            <look fileName="Мой актер или объект_#1.png" lookId="b4104f51-9067-4e11-a171-d6612b909bf6" name="Джойстик">
              <isWebRequest>false</isWebRequest>
              <valid>true</valid>
            </look>
            <look fileName="Мой актер или объект_#3.png" lookId="1622963d-1869-4d51-85c9-bbdc260de910" name="Джойстик активен">
              <isWebRequest>false</isWebRequest>
              <valid>true</valid>
            </look>
          </lookList>
          <soundList/>
          <scriptList>
            <script type="StartScript" posX="0.0" posY="0.0">
              <brickList>
                <brick type="PlaceAtBrick">
                  <brickId>f7e389f6-3302-4e8b-a3a1-012adb204a1a</brickId>
                  <commentedOut>false</commentedOut>
                  <formulaList>
                    <formula category="X_POSITION">
                      <additionalChildren/>
                      <type>NUMBER</type>
                      <value>765</value>
                    </formula>
                    <formula category="Y_POSITION">
                      <additionalChildren/>
                      <rightChild>
                        <additionalChildren/>
                        <type>NUMBER</type>
                        <value>282</value>
                      </rightChild>
                      <type>OPERATOR</type>
                      <value>MINUS</value>
                    </formula>
                  </formulaList>
                </brick>
                <brick type="ForeverBrick">
                  <brickId>db6881dc-3d2c-4009-b44f-7b6fa8df3d79</brickId>
                  <commentedOut>false</commentedOut>
                  <loopBricks>
                    <brick type="PointToBrick">
                      <brickId>89668c20-6ace-4211-85ce-e3377d6ed00a</brickId>
                      <commentedOut>false</commentedOut>
                      <pointedObject type="Sprite" spriteId="e28e73a3-ef90-475f-ba91-8f60a15447a8" name="Указатель">
                        <lookList>
                          <look fileName="Мой актер или объект_#4.png" lookId="2032d3c5-3722-454b-a3db-125e42c85a2f" name="Указатель">
                            <isWebRequest>false</isWebRequest>
                            <valid>true</valid>
                          </look>
                        </lookList>
                        <soundList/>
                        <scriptList>
                          <script type="StartScript" posX="0.0" posY="0.0">
                            <brickList>
                              <brick type="HideBrick">
                                <brickId>0fe1ada8-b2f8-42fa-85c9-9e6e9d16f1f5</brickId>
                                <commentedOut>false</commentedOut>
                              </brick>
                              <brick type="ForeverBrick">
                                <brickId>c8945d84-10f7-4ec2-b158-982cbb581a9c</brickId>
                                <commentedOut>false</commentedOut>
                                <loopBricks>
                                  <brick type="GoToBrick">
                                    <brickId>b42cd656-e6c5-489c-b277-e2532862e648</brickId>
                                    <commentedOut>false</commentedOut>
                                    <spinnerSelection>80</spinnerSelection>
                                  </brick>
                                </loopBricks>
                              </brick>
                            </brickList>
                            <commentedOut>false</commentedOut>
                            <scriptId>aa9c0d69-5eea-4016-b902-1842fa8c982f</scriptId>
                          </script>
                        </scriptList>
                        <nfcTagList/>
                        <userVariables/>
                        <userLists/>
                        <userDefinedBrickList/>
                      </pointedObject>
                    </brick>
                    <brick type="IfLogicBeginBrick">
                      <brickId>ada28758-6dbb-4cd4-b61b-05ecdec463d6</brickId>
                      <commentedOut>false</commentedOut>
                      <formulaList>
                        <formula category="IF_CONDITION">
                          <additionalChildren/>
                          <type>SENSOR</type>
                          <value>FINGER_TOUCHED</value>
                        </formula>
                      </formulaList>
                      <elseBranchBricks>
                        <brick type="SetLookBrick">
                          <brickId>7bd8c885-0af5-4e0c-b3e8-6e02cadc0f9c</brickId>
                          <commentedOut>false</commentedOut>
                          <look reference="../../../../../../../../../lookList/look"/>
                        </brick>
                      </elseBranchBricks>
                      <ifBranchBricks>
                        <brick type="SetVariableBrick">
                          <brickId>0483878f-4694-4680-a22c-9d3a1668eb93</brickId>
                          <commentedOut>false</commentedOut>
                          <formulaList>
                            <formula category="VARIABLE">
                              <additionalChildren/>
                              <type>SENSOR</type>
                              <value>MOTION_DIRECTION</value>
                            </formula>
                          </formulaList>
                          <userVariable type="UserVariable" serialization="custom">
                            <userVariable>
                              <default>
                                <initialIndex>0</initialIndex>
                                <deviceValueKey>08d76d4f-2308-4076-bf3a-453feb8dc8be</deviceValueKey>
                                <name>Указ</name>
                              </default>
                            </userVariable>
                          </userVariable>
                        </brick>
                        <brick type="SetLookBrick">
                          <brickId>6f64762e-1df5-46cd-b84d-07be46a677c6</brickId>
                          <commentedOut>false</commentedOut>
                          <look reference="../../../../../../../../../lookList/look[2]"/>
                        </brick>
                      </ifBranchBricks>
                    </brick>
                  </loopBricks>
                </brick>
              </brickList>
              <commentedOut>false</commentedOut>
              <scriptId>f101d7a0-ed64-4add-b4dd-bbb9777f8462</scriptId>
            </script>
          </scriptList>
          <nfcTagList/>
          <userVariables/>
          <userLists/>
          <userDefinedBrickList/>
        </object>
        <object reference="../object[3]/scriptList/script/brickList/brick[2]/loopBricks/brick/pointedObject"/>
        <object type="Sprite" spriteId="805c11b3-e969-47a2-ad8d-9720ea93e579" name="Мой актер или объект">
          <lookList>
            <look fileName="Мой актер или объект.png" lookId="9f57d05f-6040-4831-80c6-52db6594501c" name="Мой актер или объект">
              <isWebRequest>false</isWebRequest>
              <valid>true</valid>
            </look>
          </lookList>
          <soundList/>
          <scriptList>
            <script type="StartScript" posX="0.0" posY="0.0">
              <brickList>
                <brick type="PlaceAtBrick">
                  <brickId>99162aaa-f29e-416b-920f-9a6af81abe92</brickId>
                  <commentedOut>false</commentedOut>
                  <formulaList>
                    <formula category="X_POSITION">
                      <additionalChildren/>
                      <rightChild>
                        <additionalChildren/>
                        <type>NUMBER</type>
                        <value>688</value>
                      </rightChild>
                      <type>OPERATOR</type>
                      <value>MINUS</value>
                    </formula>
                    <formula category="Y_POSITION">
                      <additionalChildren/>
                      <type>NUMBER</type>
                      <value>283</value>
                    </formula>
                  </formulaList>
                </brick>
              </brickList>
              <commentedOut>false</commentedOut>
              <scriptId>77b84009-419a-49b3-bb17-ec45348f74e7</scriptId>
            </script>
            <script type="WhenScript" posX="0.0" posY="0.0">
              <brickList>
                <brick type="BroadcastBrick">
                  <brickId>c8a7ad78-0a09-409f-8174-88b9f7b86091</brickId>
                  <commentedOut>false</commentedOut>
                  <broadcastMessage>Предмет</broadcastMessage>
                </brick>
              </brickList>
              <commentedOut>false</commentedOut>
              <scriptId>d56ffe2f-f8e3-489b-b3f0-ac2f7583acdc</scriptId>
            </script>
          </scriptList>
          <nfcTagList/>
          <userVariables/>
          <userLists/>
          <userDefinedBrickList/>
        </object>
        <object type="Sprite" spriteId="95b82b6f-b41c-4ec8-8ede-f20df499a04b" name="Мой актер или объект (1)">
          <lookList>
            <look fileName="Мой актер или объект_#0.png" lookId="8f2a0eeb-02f5-4e6a-ad0f-c2f341e24bd9" name="Мой актер или объект (1)">
              <isWebRequest>false</isWebRequest>
              <valid>true</valid>
            </look>
          </lookList>
          <soundList/>
          <scriptList>
            <script type="StartScript" posX="0.0" posY="0.0">
              <brickList>
                <brick type="SetPhysicsObjectTypeBrick">
                  <brickId>ac749ebd-be11-435c-ae39-4e8bf0fd4cf1</brickId>
                  <commentedOut>false</commentedOut>
                  <type>DYNAMIC</type>
                </brick>
                <brick type="PlaceAtBrick">
                  <brickId>fc7cedeb-1b1d-43da-a681-b501dbaacd03</brickId>
                  <commentedOut>false</commentedOut>
                  <formulaList>
                    <formula category="X_POSITION">
                      <additionalChildren/>
                      <rightChild>
                        <additionalChildren/>
                        <type>NUMBER</type>
                        <value>170</value>
                      </rightChild>
                      <type>OPERATOR</type>
                      <value>MINUS</value>
                    </formula>
                    <formula category="Y_POSITION">
                      <additionalChildren/>
                      <rightChild>
                        <additionalChildren/>
                        <type>NUMBER</type>
                        <value>14</value>
                      </rightChild>
                      <type>OPERATOR</type>
                      <value>MINUS</value>
                    </formula>
                  </formulaList>
                </brick>
                <brick type="HideBrick">
                  <brickId>d4266ef8-7571-4df3-aa54-b792879af45e</brickId>
                  <commentedOut>false</commentedOut>
                </brick>
              </brickList>
              <commentedOut>false</commentedOut>
              <scriptId>ec2900a1-0513-43be-9592-49356552197a</scriptId>
            </script>
            <script type="BroadcastScript" posX="0.0" posY="0.0">
              <brickList>
                <brick type="CloneBrick">
                  <brickId>ca2da57f-5881-4ff6-bc11-137567462367</brickId>
                  <commentedOut>false</commentedOut>
                </brick>
                <brick type="ShowBrick">
                  <brickId>85335d24-a239-49aa-8de3-61c267708654</brickId>
                  <commentedOut>false</commentedOut>
                </brick>
              </brickList>
              <commentedOut>false</commentedOut>
              <scriptId>4d032907-2e6d-4246-930a-a187956a5881</scriptId>
              <receivedMessage>Предмет</receivedMessage>
            </script>
          </scriptList>
          <nfcTagList/>
          <userVariables/>
          <userLists/>
          <userDefinedBrickList/>
        </object>
        <object type="Sprite" spriteId="2c730de1-d59c-46c6-b3b7-18494155840e" name="Мой актер или объект (2)">
          <lookList>
            <look fileName="Мой актер или объект_#5.png" lookId="47280353-3636-4dc5-ae9a-f98d9dd90c97" name="Мой актер или объект (2)">
              <isWebRequest>false</isWebRequest>
              <valid>true</valid>
            </look>
          </lookList>
          <soundList/>
          <scriptList>
            <script type="StartScript" posX="0.0" posY="0.0">
              <brickList>
                <brick type="SetPhysicsObjectTypeBrick">
                  <brickId>d8f2c08d-6100-4e64-b210-5f03563d4d68</brickId>
                  <commentedOut>false</commentedOut>
                  <type>FIXED</type>
                </brick>
                <brick type="PlaceAtBrick">
                  <brickId>deb694f4-fa8c-4fec-ac35-3d31da3bcbef</brickId>
                  <commentedOut>false</commentedOut>
                  <formulaList>
                    <formula category="X_POSITION">
                      <additionalChildren/>
                      <rightChild>
                        <additionalChildren/>
                        <type>NUMBER</type>
                        <value>53</value>
                      </rightChild>
                      <type>OPERATOR</type>
                      <value>MINUS</value>
                    </formula>
                    <formula category="Y_POSITION">
                      <additionalChildren/>
                      <rightChild>
                        <additionalChildren/>
                        <type>NUMBER</type>
                        <value>37</value>
                      </rightChild>
                      <type>OPERATOR</type>
                      <value>MINUS</value>
                    </formula>
                  </formulaList>
                </brick>
              </brickList>
              <commentedOut>false</commentedOut>
              <scriptId>132dc7b0-75b6-450c-99bf-c15b4e5ef741</scriptId>
            </script>
          </scriptList>
          <nfcTagList/>
          <userVariables/>
          <userLists/>
          <userDefinedBrickList/>
        </object>
      </objectList>
    </scene>
  </scenes>
  <programVariableList>
    <userVariable reference="../../scenes/scene[2]/objectList/object[3]/scriptList/script/brickList/brick[2]/loopBricks/brick[2]/ifBranchBricks/brick/userVariable"/>
  </programVariableList>
  <programListOfLists/>
  <programMultiplayerVariableList/>
</program>